Metadata-Version: 2.4
Name: allianceauth-discordbot
Version: 4.1.0
Summary: Alliance Auth Modular Discord Bot
Keywords: allianceauth,eveonline
Author-email: AaronKable <aaronkable@gmail.com>
Requires-Python: >=3.8
Classifier: Environment :: Web Environment
Classifier: Framework :: Celery
Classifier: Framework :: Django
Classifier: Framework :: Django :: 4.0
Classifier: Framework :: Django :: 4.2
Classifier: Intended Audience :: Developers
Classifier: License :: OSI Approved :: MIT License
Classifier: Operating System :: OS Independent
Classifier: Programming Language :: Python
Classifier: Programming Language :: Python :: 3 :: Only
Classifier: Programming Language :: Python :: 3.8
Classifier: Programming Language :: Python :: 3.9
Classifier: Programming Language :: Python :: 3.10
Classifier: Programming Language :: Python :: 3.11
Classifier: Programming Language :: Python :: 3.12
Classifier: Programming Language :: Python :: Implementation :: CPython
Classifier: Topic :: Internet :: WWW/HTTP
Classifier: Topic :: Internet :: WWW/HTTP :: Dynamic Content
License-File: LICENSE
Requires-Dist: allianceauth>=3,<6
Requires-Dist: django-solo>=2.1,<3
Requires-Dist: pendulum>=2.1.2,<4
Requires-Dist: py-cord>2,<3
Requires-Dist: redis>=4.2,<6
Project-URL: Home, https://github.com/Solar-Helix-Independent-Transport/allianceauth-discordbot
Project-URL: Source, https://github.com/Solar-Helix-Independent-Transport/allianceauth-discordbot
Project-URL: Tracker, https://github.com/Solar-Helix-Independent-Transport/allianceauth-discordbot/issues
